nonebot_plugin_liteyukibot-0.1.9.dist-info/METADATA
nonebot_plugin_liteyukibot-0.1.9.dist-info/WHEEL
nonebot_plugin_liteyukibot-0.1.9.dist-info/licenses/LICENSE
nonebot_plugin_liteyukibot/__init__.py
nonebot_plugin_liteyukibot/liteyuki_plugins/hello_liteyuki.py
nonebot_plugin_liteyukibot/liteyuki_plugins/lifespan_monitor.py
nonebot_plugin_liteyukibot/liteyuki_plugins/register_service.py
nonebot_plugin_liteyukibot/liteyuki_plugins/to_liteyuki.py
nonebot_plugin_liteyukibot/manager.py
nonebot_plugin_liteyukibot/nonebot_sub_plugins/to_liteyuki.py
nonebot_plugin_liteyukibot-0.1.9.dist-info/RECORD
