Metadata-Version: 2.1
Name: nonebot-plugin-liteyukibot
Version: 0.1.9
Summary: nonebot-plugin-liteyukibot
Author-Email: snowykami <snowykami@outlook.com>
Requires-Python: <4.0,>=3.10
Requires-Dist: nonebot2>=2.3.3
Requires-Dist: GitPython>=3.1.43
Requires-Dist: aiohttp>=3.10.4
Requires-Dist: liteyukibot>=6.3.8
Requires-Dist: nonebot-adapter-onebot>=2.4.4
